rainbowcsv/__init__.py
rainbowcsv/__main__.py
rainbowcsv-1.0.2.dist-info/LICENSE
rainbowcsv-1.0.2.dist-info/METADATA
rainbowcsv-1.0.2.dist-info/WHEEL
rainbowcsv-1.0.2.dist-info/entry_points.txt
rainbowcsv-1.0.2.dist-info/top_level.txt
rainbowcsv-1.0.2.dist-info/RECORD
