Metadata-Version: 2.1
Name: rainbowcsv
Version: 1.0.2
Summary: Show csv in rainbow colors
Home-page: https://github.com/dannysepler/rainbowcsv
Author: Danny Sepler
Author-email: dannysepler@gmail.com
License: MIT
Project-URL: Bug Tracker, https://github.com/dannysepler/rainbowcsv/issues
Platform: UNKNOWN
Classifier: License :: OSI Approved :: MIT License
Classifier: Programming Language :: Python :: 3
Classifier: Programming Language :: Python :: 3 :: Only
Classifier: Programming Language :: Python :: 3.6
Classifier: Programming Language :: Python :: 3.7
Classifier: Programming Language :: Python :: 3.8
Classifier: Programming Language :: Python :: 3.9
Requires-Python: >=3.6.1
License-File: LICENSE
Requires-Dist: colorama
Requires-Dist: fire
